ctypesprocstuff/README.MD
ctypesprocstuff/__init__.py
ctypesprocstuff/requirements.txt
ctypesprocstuff/thirdparty.json
ctypesprocstuff-0.10.dist-info/LICENSE.rst
ctypesprocstuff-0.10.dist-info/METADATA
ctypesprocstuff-0.10.dist-info/WHEEL
ctypesprocstuff-0.10.dist-info/top_level.txt
ctypesprocstuff-0.10.dist-info/RECORD
