Metadata-Version: 2.1
Name: ctypesprocstuff
Version: 0.10
Summary: Restarts process (Windows only)
Home-page: https://github.com/hansalemaos/ctypesprocstuff
Author: Johannes Fischer
Author-email: aulasparticularesdealemaosp@gmail.com
License: MIT
Keywords: ctypes,windows
Classifier: Development Status :: 4 - Beta
Classifier: Programming Language :: Python :: 3 :: Only
Classifier: Programming Language :: Python :: 3.10
Classifier: Topic :: Software Development :: Libraries :: Python Modules
Classifier: Topic :: Utilities
License-File: LICENSE.rst
Requires-Dist: flatten-any-dict-iterable-or-whatsoever
Requires-Dist: list2tree
Requires-Dist: mymulti-key-dict
